velbus/__init__.py
velbus/command_registry.py
velbus/constants.py
velbus/controller.py
velbus/data.json
velbus/message.py
velbus/module.py
velbus/module_registry.py
velbus/parser.py
velbus/util.py
velbus/connections/__init__.py
velbus/connections/connection.py
velbus/connections/serial.py
velbus/connections/socket.py
velbus/messages/__init__.py
velbus/messages/blind_status.py
velbus/messages/bus_active.py
velbus/messages/bus_error_counter_status.py
velbus/messages/bus_error_counter_status_request.py
velbus/messages/bus_off.py
velbus/messages/channel_name_part1.py
velbus/messages/channel_name_part2.py
velbus/messages/channel_name_part3.py
velbus/messages/channel_name_request.py
velbus/messages/clear_led.py
velbus/messages/counter_status.py
velbus/messages/counter_status_request.py
velbus/messages/cover_down.py
velbus/messages/cover_off.py
velbus/messages/cover_position.py
velbus/messages/cover_up.py
velbus/messages/dimmer_channel_status.py
velbus/messages/dimmer_status.py
velbus/messages/fast_blinking_led.py
velbus/messages/interface_status_request.py
velbus/messages/kwh_status.py
velbus/messages/memo_text.py
velbus/messages/memory_data.py
velbus/messages/memory_data_block.py
velbus/messages/memory_dump_request.py
velbus/messages/meteo_raw.py
velbus/messages/module_status.py
velbus/messages/module_status_request.py
velbus/messages/module_subtype.py
velbus/messages/module_type.py
velbus/messages/module_type_request.py
velbus/messages/push_button_status.py
velbus/messages/read_data_block_from_memory.py
velbus/messages/read_data_from_memory.py
velbus/messages/receive_buffer_full.py
velbus/messages/receive_ready.py
velbus/messages/relay_status.py
velbus/messages/restore_dimmer.py
velbus/messages/sensor_settings_request.py
velbus/messages/sensor_temperature.py
velbus/messages/set_date.py
velbus/messages/set_daylight_saving.py
velbus/messages/set_dimmer.py
velbus/messages/set_led.py
velbus/messages/set_realtime_clock.py
velbus/messages/set_temperature.py
python_velbus-2.1.14.dist-info/LICENSE
python_velbus-2.1.14.dist-info/METADATA
python_velbus-2.1.14.dist-info/WHEEL
python_velbus-2.1.14.dist-info/top_level.txt
python_velbus-2.1.14.dist-info/RECORD
