Metadata-Version: 2.1
Name: python-velbus
Version: 2.1.14
Summary: Python Library for the Velbus protocol
Home-page: https://github.com/thomasdelaet/python-velbus
Author: Thomas Delaet
Author-email: thomas@delaet.org
License: MIT
Keywords: home,velbus,automation
Platform: any
Classifier: Development Status :: 4 - Beta
Classifier: Intended Audience :: Developers
Classifier: License :: OSI Approved :: MIT License
Classifier: Natural Language :: English
Classifier: Operating System :: OS Independent
Classifier: Programming Language :: Python
Classifier: Topic :: Home Automation
Requires-Dist: pyserial (>=3.4)
